wikiapi/__init__.py
wikiapi/wikiapi.py
wikiapi-2.1.0.dist-info/METADATA
wikiapi-2.1.0.dist-info/WHEEL
wikiapi-2.1.0.dist-info/top_level.txt
wikiapi-2.1.0.dist-info/RECORD
