Metadata-Version: 2.4
Name: wikiapi
Version: 2.1.0
Summary: A basic python library enabling access to Wikipedia.org's search results and article content.
Author: Richard O'Dwyer
Author-email: richard@richard.do
License: Creative Commons Attribution-Noncommercial-Share Alike license
Classifier: Intended Audience :: Developers
Classifier: Operating System :: OS Independent
Classifier: Programming Language :: Python
Classifier: Programming Language :: Python :: 3
Classifier: Topic :: Internet :: WWW/HTTP
Requires-Dist: wheel>=0.31.0
Requires-Dist: pyquery>=1.2.9
Requires-Dist: requests>=2.5.1
Requires-Dist: beautifulsoup4>=4.0.1
Requires-Dist: six>=1.11.0
Requires-Dist: pandas>=1.0.0
Requires-Dist: Unidecode>=1.1.1
Dynamic: author
Dynamic: author-email
Dynamic: classifier
Dynamic: description
Dynamic: license
Dynamic: requires-dist
Dynamic: summary
